README.md
setup.py
ingestion/__init__.py
ingestion/api_client.py
ingestion/configuration.py
ingestion/exceptions.py
ingestion/rest.py
ingestion/api/__init__.py
ingestion/api/default_api.py
ingestion/api/result_api.py
ingestion/api/summary_api.py
ingestion/api/thread_api.py
ingestion/models/__init__.py
ingestion/models/modelthread.py
ingestion/models/problem_formulation.py
ingestion/models/scenario.py
ingestion/models/summary.py
ingestion/models/summary_response.py
ingestion/models/thread.py
ingestion_api.egg-info/PKG-INFO
ingestion_api.egg-info/SOURCES.txt
ingestion_api.egg-info/dependency_links.txt
ingestion_api.egg-info/requires.txt
ingestion_api.egg-info/top_level.txt
test/__init__.py
test/test_default_api.py
test/test_modelthread.py
test/test_problem_formulation.py
test/test_result_api.py
test/test_scenario.py
test/test_summary.py
test/test_summary_api.py
test/test_summary_response.py
test/test_thread.py
test/test_thread_api.py