Metadata-Version: 1.0
Name: ingestion-api
Version: 1.3.3
Summary: ingestion
Home-page: https://pypi.org/project/ingestion-api/
Author: UNKNOWN
Author-email: UNKNOWN
License: UNKNOWN
Keywords: OpenAPI,OpenAPI-Generator,ingestion
Platform: UNKNOWN
